topsispk/__init__.py
topsispk/topsis.py
toposis_parth_101853019-1.2.1.dist-info/LICENSE.txt
toposis_parth_101853019-1.2.1.dist-info/METADATA
toposis_parth_101853019-1.2.1.dist-info/WHEEL
toposis_parth_101853019-1.2.1.dist-info/top_level.txt
toposis_parth_101853019-1.2.1.dist-info/RECORD
