Metadata-Version: 2.1
Name: toposis-parth-101853019
Version: 1.2.1
Summary: TOPSIS is an algorithm for the determination of the best choice out of many using Positive Ideal Solution and Negative Ideal
Home-page: https://github.com/you/your_package
Author: Parth Khandelwal
Author-email: parthmanan1999@gmail.com
License: Apache License 2.0
Platform: UNKNOWN
Requires-Dist: numpy
Requires-Dist: pandas
Requires-Dist: tabulate
Requires-Dist: scipy
